firewheel_repo_linux/linux/.gitignore
firewheel_repo_linux/linux/MANIFEST
firewheel_repo_linux/linux/README.rst
firewheel_repo_linux/linux/model_component_objects.py
firewheel_repo_linux/linux/INSTALL/tasks.yml
firewheel_repo_linux/linux/INSTALL/vars.yml
firewheel_repo_linux/linux/vm_resources/chpasswd.sh
firewheel_repo_linux/linux/vm_resources/configure_ips.sh
firewheel_repo_linux/linux/vm_resources/set_hostname.sh
firewheel_repo_linux/linux/vm_resources/set_netplan_interfaces.sh
firewheel_repo_linux/linux/vm_resources/set_ulimit.sh
firewheel_repo_linux/ubuntu/bionic/.gitignore
firewheel_repo_linux/ubuntu/bionic/MANIFEST
firewheel_repo_linux/ubuntu/bionic/README.rst
firewheel_repo_linux/ubuntu/bionic/model_component_objects.py
firewheel_repo_linux/ubuntu/bionic/INSTALL/tasks.yml
firewheel_repo_linux/ubuntu/bionic/INSTALL/vars.yml
firewheel_repo_linux/ubuntu/bionic/images/.gitkeep
firewheel_repo_linux/ubuntu/jammy/.gitignore
firewheel_repo_linux/ubuntu/jammy/MANIFEST
firewheel_repo_linux/ubuntu/jammy/README.rst
firewheel_repo_linux/ubuntu/jammy/model_component_objects.py
firewheel_repo_linux/ubuntu/jammy/INSTALL/tasks.yml
firewheel_repo_linux/ubuntu/jammy/INSTALL/vars.yml
firewheel_repo_linux/ubuntu/jammy/images/.gitkeep
firewheel_repo_linux/ubuntu/jammy/vm_resources/debs/.gitkeep
firewheel_repo_linux/ubuntu/trusty/.gitignore
firewheel_repo_linux/ubuntu/trusty/MANIFEST
firewheel_repo_linux/ubuntu/trusty/README.rst
firewheel_repo_linux/ubuntu/trusty/model_component_objects.py
firewheel_repo_linux/ubuntu/trusty/INSTALL/tasks.yml
firewheel_repo_linux/ubuntu/trusty/INSTALL/vars.yml
firewheel_repo_linux/ubuntu/trusty/images/.gitkeep
firewheel_repo_linux/ubuntu/trusty/vm_resources/configure_nginx_trusty.py
firewheel_repo_linux/ubuntu/trusty/vm_resources/debs/.gitignore
firewheel_repo_linux/ubuntu/trusty/vm_resources/debs/.gitkeep
firewheel_repo_linux/ubuntu/ubuntu/.gitignore
firewheel_repo_linux/ubuntu/ubuntu/MANIFEST
firewheel_repo_linux/ubuntu/ubuntu/README.rst
firewheel_repo_linux-3.0.0.dist-info/licenses/LICENSE
firewheel_repo_linux-3.0.0.dist-info/METADATA
firewheel_repo_linux-3.0.0.dist-info/WHEEL
firewheel_repo_linux-3.0.0.dist-info/entry_points.txt
firewheel_repo_linux-3.0.0.dist-info/top_level.txt
firewheel_repo_linux-3.0.0.dist-info/RECORD
